LICENSE
MANIFEST.in
README.md
setup.cfg
setup.py
chemolab/__init__.py
chemolab.egg-info/PKG-INFO
chemolab.egg-info/SOURCES.txt
chemolab.egg-info/dependency_links.txt
chemolab.egg-info/top_level.txt
chemolab/core/unicode.py
chemolab/elements/element.py
chemolab/elements/element_data.py
chemolab/elements/data/Al.xml
chemolab/elements/data/Ar.xml
chemolab/elements/data/B.xml
chemolab/elements/data/Be.xml
chemolab/elements/data/C.xml
chemolab/elements/data/Ca.xml
chemolab/elements/data/Cl.xml
chemolab/elements/data/F.xml
chemolab/elements/data/H.xml
chemolab/elements/data/He.xml
chemolab/elements/data/K.xml
chemolab/elements/data/Li.xml
chemolab/elements/data/Mg.xml
chemolab/elements/data/N.xml
chemolab/elements/data/Na.xml
chemolab/elements/data/Ne.xml
chemolab/elements/data/O.xml
chemolab/elements/data/P.xml
chemolab/elements/data/S.xml
chemolab/elements/data/Si.xml