Metadata-Version: 1.2
Name: chemolab
Version: 1.0.0b1
Summary: ChemoLab is an educational based chemistry library for Python
Home-page: https://github.com/MeleiDigitalMedia/ChemoLab/
Author: MeleiDigitalMedia
Author-email: meleidigitalmedia@gmail.com
License: MIT
Download-URL: https://github.com/MeleiDigitalMedia/ChemoLab/archive/1.0.0-beta_001.tar.gz
Platform: UNKNOWN
Requires-Python: >=3.8
